setup.py
client/__init__.py
client/client.py
client/client/__init__.py
client/client/add_contact_gui.py
client/client/client_database.py
client/client/del_contact_gui.py
client/client/main_window.py
client/client/main_window_conv.py
client/client/transport.py
client/client/welcome_gui.py
client/common/__init__.py
client/common/constants.py
client/common/decos.py
client/common/descriptors.py
client/common/errors.py
client/common/functions.py
client/common/metacls.py
client/log/__init__.py
client/log/log_config/__init__.py
client/log/log_config/client_log_config.py
client/project_tests/__init__.py
client/project_tests/test_client.py
client/project_tests/test_functions.py
client/project_tests/test_server.py
msg_client_02_21.egg-info/PKG-INFO
msg_client_02_21.egg-info/SOURCES.txt
msg_client_02_21.egg-info/dependency_links.txt
msg_client_02_21.egg-info/requires.txt
msg_client_02_21.egg-info/top_level.txt