Metadata-Version: 1.0
Name: msg-client-02-21
Version: 0.0.3
Summary: The client part of the course project "Messenger"
Home-page: UNKNOWN
Author: Kostitsyn Aleksandr
Author-email: kostitsin.a@mail.ru
License: UNKNOWN
Platform: UNKNOWN
